{
  "zip": "32092",
  "name": "World Golf Village",
  "computed_at": "2026-04-24T11:34:53.634Z",
  "demographics": {
    "population": 48288,
    "median_household_income": 122655,
    "median_home_value": 464800,
    "owner_occupied_pct": 88.4,
    "total_households": 16772,
    "consumer_profile": "affluent_established",
    "wfh_pct": 25,
    "daytime_pop_multiplier": 1.15,
    "daytime_demand_population": 55531,
    "retiree_index": 0,
    "vacancy_rate_pct": 8.9,
    "family_hh_pct": 84,
    "affluence_pct": 70,
    "ultra_affluence_pct": 37,
    "renovation_wave": "moderate",
    "housing_age_profile": "active_growth",
    "new_build_pct": 37
  },
  "restaurant_capacity": {
    "restaurant_count": 2,
    "total_businesses": 101,
    "estimated_daily_meal_demand": 34429,
    "market_capacity_meals_day": 800,
    "capture_rate_pct": 2,
    "saturation_status": "undersupplied",
    "restaurants_market_can_support": 86,
    "gap_count": 84,
    "tier_breakdown": {
      "budget": 1,
      "midrange": 1,
      "upscale": 0,
      "fine": 0,
      "unknown": 0
    },
    "meals_out_per_person_per_day": 0.62
  },
  "market_gaps": {
    "price_tier_gaps": [
      {
        "tier": "midrange",
        "demand_pct": 45,
        "expected_count": 39,
        "actual_count": 1,
        "gap": 38,
        "status": "undersupplied",
        "description": "$12–$25 — casual dining"
      },
      {
        "tier": "upscale",
        "demand_pct": 30,
        "expected_count": 26,
        "actual_count": 0,
        "gap": 26,
        "status": "undersupplied",
        "description": "$25–$60 — full service, bar"
      },
      {
        "tier": "budget",
        "demand_pct": 15,
        "expected_count": 13,
        "actual_count": 1,
        "gap": 12,
        "status": "undersupplied",
        "description": "Under $12 — fast casual / counter service"
      },
      {
        "tier": "fine",
        "demand_pct": 10,
        "expected_count": 9,
        "actual_count": 0,
        "gap": 9,
        "status": "undersupplied",
        "description": "$60+ — fine dining / tasting menu"
      }
    ],
    "school_count": 0,
    "top_gap": {
      "tier": "midrange",
      "demand_pct": 45,
      "expected_count": 39,
      "actual_count": 1,
      "gap": 38,
      "status": "undersupplied",
      "description": "$12–$25 — casual dining"
    }
  },
  "growth_trajectory": {
    "state": "stable",
    "label": "Stable Mixed",
    "confidence": "low",
    "school_count": 0,
    "owner_occupied_pct": 88.4,
    "infrastructure_momentum": 0,
    "active_construction": 0,
    "active_road_projects": 0,
    "flood_zone_pct": 0
  },
  "top_questions": [
    {
      "question": "Is there room for another restaurant in World Golf Village?",
      "answer": "Yes — World Golf Village is undersupplied. 2 restaurants cover only ~2% of daily meal demand. Biggest gap: midrange dining ($12–$25 — casual dining).",
      "signal_strength": "strong",
      "category": "restaurant_gap"
    },
    {
      "question": "Is World Golf Village growing, stable, or becoming empty nest?",
      "answer": "Stable established suburb. Predictable demand, lower risk, but also slower upside. Proven concepts outperform experimental ones here.",
      "signal_strength": "low",
      "category": "growth_trajectory"
    },
    {
      "question": "What category is most missing in World Golf Village?",
      "answer": "Midrange dining is the biggest gap — income distribution suggests 45% of meals should be in that tier, but only 1 of the expected 39 spots exist. $12–$25 — casual dining.",
      "signal_strength": "moderate",
      "category": "category_gap"
    }
  ],
  "oracle_narrative": "World Golf Village (pop. 48,288, median HHI $122,655) is stable mixed. With 2 food businesses serving an estimated 34429 meals/day demand, the market is undersupplied (2% capture rate). Biggest price-tier gap: midrange dining — 1 exist vs. 39 expected at this income level.",
  "vertical_gaps": [],
  "data_sources": {
    "businesses_indexed": 101,
    "has_spending_zone": true,
    "has_bedrock": false,
    "has_ocean_floor": false,
    "has_census_layer": false,
    "has_acs": false,
    "has_zbp": false,
    "has_cbp": false,
    "vertical_gap_count": 0
  },
  "economic_layer": null,
  "trend": null
}